{
  "cli": {
    "version": ">= 16.0.0",
    "appVersionSource": "local"
  },
  "build": {
    "ios-simulator": {
      "ios": {
        "simulator": true
      },
      "channel": "preview"
    },
    "preview": {
      "distribution": "internal",
      "channel": "preview"
    },
    "production": {
      "autoIncrement": false,
      "channel": "production"
    }
  },
  "submit": {
    "production": {
      "ios": {
        "ascAppId": "6764521345",
        "appleTeamId": "27V75H7TGZ"
      }
    }
  }
}
